[
  {
    "id": "zs-jr-001",
    "bank": ["工商银行", "建设银行", "中国银行", "农业银行"],
    "category": "专业知识",
    "subcategory": "金融知识",
    "difficulty": "中等",
    "question": "以下哪项是中央银行的货币政策工具？",
    "options": ["A. 税收政策", "B. 公开市场操作", "C. 政府支出", "D. 发行国债"],
    "answer": "B",
    "analysis": "公开市场操作是中央银行三大货币政策工具之一（存款准备金率、再贴现政策、公开市场操作）。税收政策、政府支出属于财政政策工具。发行国债是财政部职能。",
    "source": "银行招聘专业知识题库"
  },
  {
    "id": "zs-jr-002",
    "bank": ["工商银行", "建设银行", "中国银行"],
    "category": "专业知识",
    "subcategory": "金融知识",
    "difficulty": "中等",
    "question": "凯恩斯认为，人们持有货币的动机不包括以下哪项？",
    "options": ["A. 交易动机", "B. 预防动机", "C. 投资动机", "D. 投机动机"],
    "answer": "C",
    "analysis": "凯恩斯货币需求理论提出三大动机：交易动机（日常交易）、预防动机（应对意外支出）和投机动机（捕捉利率变化机会）。'投资动机'不属于凯恩斯提出的货币需求动机。",
    "source": "银行招聘金融知识真题"
  },
  {
    "id": "zs-jr-003",
    "bank": ["工商银行", "建设银行", "中国银行", "农业银行"],
    "category": "专业知识",
    "subcategory": "金融知识",
    "difficulty": "简单",
    "question": "商业银行最核心的功能是：",
    "options": ["A. 信用中介", "B. 支付中介", "C. 信用创造", "D. 金融服务"],
    "answer": "A",
    "analysis": "信用中介是商业银行最基本的核心功能，即通过吸收存款和发放贷款，充当资金盈余者和资金短缺者之间的中介。支付中介、信用创造和金融服务都是在信用中介基础上派生出来的。",
    "source": "银行招聘金融基础知识"
  },
  {
    "id": "zs-jr-004",
    "bank": ["工商银行", "中国银行", "建设银行"],
    "category": "专业知识",
    "subcategory": "金融知识",
    "difficulty": "中等",
    "question": "某债券实际预期收益率为6%，预期通货膨胀率约为2%，则该债券的名义收益率约为：",
    "options": ["A. 4%", "B. 6%", "C. 8%", "D. 10%"],
    "answer": "C",
    "analysis": "根据费雪效应，名义利率=实际利率+预期通货膨胀率。即名义收益率=6%+2%=8%。名义收益率反映未扣除通胀因素的收益率。",
    "source": "银行招聘金融知识真题"
  },
  {
    "id": "zs-jr-005",
    "bank": ["工商银行", "建设银行", "中国银行"],
    "category": "专业知识",
    "subcategory": "金融知识",
    "difficulty": "困难",
    "question": "以下关于货币政策传导机制的说法，正确的是：",
    "options": ["A. 利率渠道中，货币供给增加导致利率上升", "B. 信贷渠道中，紧缩货币政策会减少银行贷款供给", "C. 资产价格渠道中，货币供给减少会推高资产价格", "D. 汇率渠道中，利率下降会导致本币升值"],
    "answer": "B",
    "analysis": "A错误：货币供给增加一般导致利率下降。C错误：货币供给减少会压低资产价格。D错误：利率下降会导致本币贬值而非升值。B正确：紧缩货币政策减少银行准备金，从而减少可贷资金和贷款供给。",
    "source": "银行招聘金融知识真题"
  },
  {
    "id": "zs-jr-006",
    "bank": ["建设银行", "农业银行", "交通银行"],
    "category": "专业知识",
    "subcategory": "金融知识",
    "difficulty": "中等",
    "question": "以下哪项属于商业银行的表外业务？",
    "options": ["A. 吸收存款", "B. 发放贷款", "C. 银行承兑汇票", "D. 证券投资"],
    "answer": "C",
    "analysis": "表外业务是指商业银行从事的不列入资产负债表但可能产生损益的业务。银行承兑汇票是典型的表外业务（或有负债）。吸收存款和发放贷款分别属于负债业务和资产业务，均需列入表内。",
    "source": "银行招聘专业笔试题库"
  },
  {
    "id": "zs-jr-007",
    "bank": ["中国银行", "工商银行", "建设银行"],
    "category": "专业知识",
    "subcategory": "金融知识",
    "difficulty": "中等",
    "question": "国际收支平衡表中，以下哪项属于资本与金融账户？",
    "options": ["A. 货物贸易出口", "B. 服务贸易收入", "C. 外商直接投资", "D. 侨汇收入"],
    "answer": "C",
    "analysis": "国际收支平衡表包括经常账户和资本与金融账户。外商直接投资（FDI）属于金融账户。货物贸易、服务贸易、侨汇收入均属于经常账户。",
    "source": "银行招聘金融知识题库"
  },
  {
    "id": "zs-jr-008",
    "bank": ["工商银行", "建设银行", "中国银行"],
    "category": "专业知识",
    "subcategory": "金融知识",
    "difficulty": "简单",
    "question": "存款保险制度中，同一存款人在同一家投保机构的最高偿付限额为人民币：",
    "options": ["A. 30万元", "B. 50万元", "C. 80万元", "D. 100万元"],
    "answer": "B",
    "analysis": "我国《存款保险条例》规定，存款保险最高偿付限额为人民币50万元。这一标准覆盖了99%以上存款人的全部存款，在保护中小存款人利益和维护金融稳定之间取得平衡。",
    "source": "银行招聘金融常识"
  },
  {
    "id": "zs-jj-009",
    "bank": ["工商银行", "建设银行", "农业银行"],
    "category": "专业知识",
    "subcategory": "经济常识",
    "difficulty": "中等",
    "question": "\"太多的货币追逐太少的商品\"描述的是哪种类型的通货膨胀？",
    "options": ["A. 需求拉上型通货膨胀", "B. 成本推动型通货膨胀", "C. 结构性通货膨胀", "D. 输入型通货膨胀"],
    "answer": "A",
    "analysis": "\"太多的货币追逐太少的商品\"是需求拉上型通货膨胀的经典描述，指总需求超过总供给导致物价持续上涨。成本推动型强调生产成本上升推动物价上涨；结构性通货膨胀源于经济结构失衡。",
    "source": "银行招聘经济常识真题"
  },
  {
    "id": "zs-jj-010",
    "bank": ["工商银行", "建设银行", "中国银行"],
    "category": "专业知识",
    "subcategory": "经济常识",
    "difficulty": "中等",
    "question": "用收入法核算GDP时，以下哪项属于非生产要素收入？",
    "options": ["A. 工资", "B. 利息", "C. 企业间接税", "D. 利润"],
    "answer": "C",
    "analysis": "收入法核算GDP：GDP=工资+利息+利润+租金+企业间接税+折旧。企业间接税（如增值税、消费税）不属于生产要素的收入，而是政府对生产征收的税收，属于非生产要素收入项目。",
    "source": "银行招聘经济常识真题"
  },
  {
    "id": "zs-jj-011",
    "bank": ["建设银行", "农业银行", "邮储银行"],
    "category": "专业知识",
    "subcategory": "经济常识",
    "difficulty": "简单",
    "question": "在完全竞争市场中，企业在短期内获得最大利润的条件是：",
    "options": ["A. 边际收益大于边际成本", "B. 边际收益等于边际成本", "C. 平均收益等于平均成本", "D. 总收益等于总成本"],
    "answer": "B",
    "analysis": "无论何种市场结构，企业实现利润最大化的均衡条件都是边际收益等于边际成本（MR=MC）。当MR>MC时，增加产量可增加利润；当MR<MC时，减少产量可增加利润。",
    "source": "银行招聘经济基础知识"
  },
  {
    "id": "zs-jj-012",
    "bank": ["工商银行", "建设银行", "中国银行"],
    "category": "专业知识",
    "subcategory": "经济常识",
    "difficulty": "困难",
    "question": "在封闭经济条件下，总需求的构成一般不包括：",
    "options": ["A. 消费需求", "B. 投资需求", "C. 政府购买", "D. 出口需求"],
    "answer": "D",
    "analysis": "封闭经济中没有国际贸易，因此总需求=消费+投资+政府购买，不包括出口（出口是开放经济中的总需求组成部分）。四部门经济总需求=消费+投资+政府购买+净出口。",
    "source": "银行招聘经济常识真题"
  },
  {
    "id": "zs-jj-013",
    "bank": ["工商银行", "建设银行", "农业银行", "交通银行"],
    "category": "专业知识",
    "subcategory": "经济常识",
    "difficulty": "中等",
    "question": "当中央银行提高法定存款准备金率时，可能产生的效果是：",
    "options": ["A. 商业银行可贷资金增加", "B. 货币乘数增大", "C. 市场货币供应量减少", "D. 利率下降"],
    "answer": "C",
    "analysis": "提高法定存款准备金率意味着商业银行需缴存更多准备金，可贷资金减少，货币乘数变小，从而市场货币供应量减少，属于紧缩性货币政策。利率通常会上升而非下降。",
    "source": "银行招聘经济金融真题"
  },
  {
    "id": "zs-kj-014",
    "bank": ["工商银行", "建设银行", "中国银行"],
    "category": "专业知识",
    "subcategory": "会计财务",
    "difficulty": "中等",
    "question": "以下会计要素中，属于资产负债表要素的是：",
    "options": ["A. 收入", "B. 费用", "C. 资产", "D. 利润"],
    "answer": "C",
    "analysis": "会计六大要素中，资产、负债、所有者权益是资产负债表要素（反映财务状况），收入、费用、利润是利润表要素（反映经营成果）。C选项'资产'属于资产负债表要素。",
    "source": "银行招聘会计基础知识"
  },
  {
    "id": "zs-kj-015",
    "bank": ["工商银行", "建设银行", "中国银行", "农业银行"],
    "category": "专业知识",
    "subcategory": "会计财务",
    "difficulty": "简单",
    "question": "商业银行的贷款损失准备金属于：",
    "options": ["A. 资产", "B. 负债", "C. 所有者权益", "D. 资产备抵账户"],
    "answer": "D",
    "analysis": "贷款损失准备金是商业银行资产（贷款）的备抵账户，用于覆盖贷款可能发生的损失。在资产负债表中，贷款损失准备金作为贷款的减项列示，反映贷款的账面价值。",
    "source": "银行招聘会计专业知识"
  },
  {
    "id": "zs-kj-016",
    "bank": ["工商银行", "建设银行", "中国银行"],
    "category": "专业知识",
    "subcategory": "会计财务",
    "difficulty": "中等",
    "question": "企业采用权责发生制核算，以下哪项应在当期确认为收入？",
    "options": ["A. 收到客户预付的货款", "B. 销售商品已发出但款项未收到", "C. 收到银行定期存款利息", "D. 收到股东投资款"],
    "answer": "B",
    "analysis": "权责发生制以权利和义务的发生为标准确认收入和费用。商品已发出、风险报酬已转移，即使款项未收到也应在当期确认收入。A预收货款应确认为负债；C应在实际收到时确认或按权责确认；D属于所有者权益增加，不是收入。",
    "source": "银行招聘会计基础真题"
  },
  {
    "id": "zs-kj-017",
    "bank": ["建设银行", "农业银行", "邮储银行"],
    "category": "专业知识",
    "subcategory": "会计财务",
    "difficulty": "困难",
    "question": "企业因向关联方提供借款而收取的利息收入，在现金流量表中应列入：",
    "options": ["A. 经营活动现金流量", "B. 投资活动现金流量", "C. 筹资活动现金流量", "D. 不涉及现金收支"],
    "answer": "B",
    "analysis": "企业对外提供借款属于投资活动，由此产生的利息收入属于投资活动产生的现金流量。根据企业会计准则，收取的利息和股利通常归类为投资活动现金流量。",
    "source": "银行招聘会计财务真题"
  },
  {
    "id": "zs-kj-018",
    "bank": ["工商银行", "建设银行", "中国银行"],
    "category": "专业知识",
    "subcategory": "会计财务",
    "difficulty": "中等",
    "question": "某企业年末应收账款余额为500万元，按账龄分析法计提坏账准备。其中账龄1年以内300万元（计提比例5%），1-2年150万元（计提比例10%），2年以上50万元（计提比例20%）。该企业年末应计提的坏账准备为：",
    "options": ["A. 25万元", "B. 30万元", "C. 35万元", "D. 40万元"],
    "answer": "D",
    "analysis": "应计提坏账准备=300×5%+150×10%+50×20%=15+15+10=40万元。注意：如坏账准备账户已有余额，则需扣除已有余额后补提。本题为计算应计提总额，答案为40万元。",
    "source": "银行招聘会计专业知识"
  },
  {
    "id": "zs-yw-019",
    "bank": ["工商银行", "建设银行", "中国银行", "农业银行"],
    "category": "专业知识",
    "subcategory": "银行业务基础",
    "difficulty": "简单",
    "question": "银行承兑汇票的付款期限最长不超过：",
    "options": ["A. 3个月", "B. 6个月", "C. 9个月", "D. 12个月"],
    "answer": "B",
    "analysis": "根据《票据法》规定，银行承兑汇票的付款期限（汇票到期日）自出票日起最长不得超过6个月。这是为了控制票据风险，保证资金周转效率。",
    "source": "银行招聘业务基础真题"
  },
  {
    "id": "zs-yw-020",
    "bank": ["工商银行", "中国银行", "建设银行"],
    "category": "专业知识",
    "subcategory": "银行业务基础",
    "difficulty": "中等",
    "question": "以下关于LPR（贷款市场报价利率）的说法，错误的是：",
    "options": ["A. LPR由中国人民银行直接制定", "B. LPR分为1年期和5年期以上两个品种", "C. LPR是商业银行对最优质客户的贷款利率", "D. 各银行新发放贷款主要参考LPR定价"],
    "answer": "A",
    "analysis": "LPR是由18家报价行在公开市场操作利率（MLF利率）基础上加点报价形成，并非由中国人民银行直接制定。央行负责指导和管理LPR形成机制。B、C、D均正确。",
    "source": "银行招聘银行业务基础真题"
  },
  {
    "id": "zs-yw-021",
    "bank": ["工商银行", "建设银行", "农业银行", "邮储银行"],
    "category": "专业知识",
    "subcategory": "银行业务基础",
    "difficulty": "中等",
    "question": "商业银行在办理个人住房贷款时，首付款比例由以下哪个因素决定？",
    "options": ["A. 借款人信用记录", "B. 中国人民银行政策规定", "C. 商业银行自主决定", "D. 地方政府规定"],
    "answer": "B",
    "analysis": "个人住房贷款首付款比例由中国人民银行根据国家宏观调控需要统一规定最低比例，各商业银行在实际执行中可根据借款人信用状况等因素适当上浮。央行目前规定的首套房贷最低首付比例为20%。",
    "source": "银行招聘银行业务基础"
  },
  {
    "id": "zs-yw-022",
    "bank": ["工商银行", "建设银行", "中国银行", "农业银行"],
    "category": "专业知识",
    "subcategory": "银行业务基础",
    "difficulty": "简单",
    "question": "以下哪项不属于商业银行的中间业务？",
    "options": ["A. 支付结算业务", "B. 代理业务", "C. 银行卡业务", "D. 吸收存款"],
    "answer": "D",
    "analysis": "中间业务是银行不运用自有资金、不承担或不直接承担信用风险，以代理人身份提供服务的业务，包括支付结算、代理业务、银行卡业务等。吸收存款属于负债业务，不是中间业务。",
    "source": "银行招聘业务基础真题"
  },
  {
    "id": "zs-jsj-023",
    "bank": ["工商银行", "建设银行", "中国银行", "农业银行"],
    "category": "专业知识",
    "subcategory": "计算机基础",
    "difficulty": "简单",
    "question": "在计算机系统中，CPU的主要功能是：",
    "options": ["A. 存储数据", "B. 运算和控制", "C. 输入输出", "D. 网络通信"],
    "answer": "B",
    "analysis": "CPU（中央处理器）是计算机的核心部件，主要功能是运算（算术运算和逻辑运算）和控制（指令译码和执行控制）。存储由内存负责，I/O由外部设备负责。",
    "source": "银行招聘计算机基础真题"
  },
  {
    "id": "zs-jsj-024",
    "bank": ["工商银行", "建设银行", "中国银行"],
    "category": "专业知识",
    "subcategory": "计算机基础",
    "difficulty": "中等",
    "question": "以下哪种网络设备工作在网络层（第三层）？",
    "options": ["A. 集线器（Hub）", "B. 交换机（Switch）", "C. 路由器（Router）", "D. 中继器（Repeater）"],
    "answer": "C",
    "analysis": "OSI模型中，集线器和中继器工作在物理层（第一层），交换机工作在数据链路层（第二层），路由器工作在网络层（第三层），负责数据包的路由选择和转发。",
    "source": "银行招聘计算机基础"
  },
  {
    "id": "zs-jsj-025",
    "bank": ["工商银行", "建设银行", "中国银行", "农业银行"],
    "category": "专业知识",
    "subcategory": "计算机基础",
    "difficulty": "中等",
    "question": "在数据库中，SQL语句\"SELECT * FROM customers WHERE city LIKE '北%'\"的作用是：",
    "options": ["A. 查询城市名称以'北'开头的客户", "B. 查询城市名称包含'北'字的客户", "C. 查询城市名称以'北'结尾的客户", "D. 查询城市名称为'北'的客户"],
    "answer": "A",
    "analysis": "LIKE语句中，'%'是通配符，表示任意长度的字符。'北%'表示以'北'开头的任意字符串。B应使用'%北%'，C应使用'%北'，D应使用'北'（精确匹配）。",
    "source": "银行招聘计算机基础真题"
  },
  {
    "id": "zs-yw-026",
    "bank": ["工商银行", "建设银行", "农业银行"],
    "category": "专业知识",
    "subcategory": "银行业务基础",
    "difficulty": "中等",
    "question": "以下关于银行信用卡的说法，错误的是：",
    "options": ["A. 信用卡具有透支消费功能", "B. 信用卡分期付款需要支付手续费", "C. 信用卡取现没有免息期", "D. 信用卡额度越高越好"],
    "answer": "D",
    "analysis": "信用卡额度并非越高越好。额度应与持卡人的消费需求和还款能力相匹配，过高额度可能导致过度消费和逾期风险。A正确：信用卡核心功能是透支消费。B正确：分期付款需支付分期手续费。C正确：信用卡取现自取现当日起计息，无免息期。",
    "source": "银行招聘业务基础真题"
  },
  {
    "id": "zs-yw-027",
    "bank": ["工商银行", "建设银行", "中国银行", "农业银行"],
    "category": "专业知识",
    "subcategory": "银行业务基础",
    "difficulty": "简单",
    "question": "我国银行间同业拆借市场的主要功能是：",
    "options": ["A. 股票交易", "B. 债券发行", "C. 金融机构短期资金融通", "D. 外汇买卖"],
    "answer": "C",
    "analysis": "同业拆借市场是金融机构之间进行短期资金融通的市场，主要用于调剂头寸余缺、满足短期流动性需求。我国银行间同业拆借期限一般在1天到1年之间。",
    "source": "银行招聘银行业务基础"
  },
  {
    "id": "zs-jr-028",
    "bank": ["工商银行", "中国银行", "建设银行"],
    "category": "专业知识",
    "subcategory": "金融知识",
    "difficulty": "困难",
    "question": "资本资产定价模型（CAPM）中，β系数衡量的是：",
    "options": ["A. 资产的总体风险", "B. 资产的系统性风险", "C. 资产的非系统性风险", "D. 资产的流动性风险"],
    "answer": "B",
    "analysis": "β系数衡量资产收益对市场收益变动的敏感程度，即系统性风险（市场风险）。β=1表示与市场同涨同跌，β>1表示波动大于市场，β<1表示波动小于市场。非系统性风险可通过分散投资消除。",
    "source": "银行招聘金融知识真题"
  },
  {
    "id": "zs-yw-029",
    "bank": ["建设银行", "农业银行", "邮储银行"],
    "category": "专业知识",
    "subcategory": "银行业务基础",
    "difficulty": "中等",
    "question": "在银行风险管理中，操作风险不包括以下哪项？",
    "options": ["A. 内部欺诈", "B. 外部欺诈", "C. 市场利率变动", "D. 系统故障"],
    "answer": "C",
    "analysis": "操作风险是指由不完善或有问题的内部程序、员工、信息科技系统以及外部事件所造成损失的风险，包括内部欺诈、外部欺诈、系统故障等。市场利率变动属于市场风险，不是操作风险。",
    "source": "银行招聘风险管理知识"
  },
  {
    "id": "zs-jj-030",
    "bank": ["工商银行", "建设银行", "中国银行", "农业银行"],
    "category": "专业知识",
    "subcategory": "经济常识",
    "difficulty": "中等",
    "question": "经济学中的\"边际效用递减规律\"是指：",
    "options": ["A. 总效用随消费量增加而递减", "B. 每增加一单位消费所带来的效用增量递减", "C. 边际效用始终为正", "D. 总效用递减时边际效用递增"],
    "answer": "B",
    "analysis": "边际效用递减规律是指在一定时间内，在其他商品消费量不变的情况下，随着消费者对某种商品消费量的连续增加，每增加一单位消费所带来的效用增量（边际效用）是递减的。A错误：总效用一般递增但增速放缓。C错误：边际效用可为负。D错误：与规律相反。",
    "source": "银行招聘经济常识"
  }
]
